pyprt/__init__.py
pyprt/pyprt/__init__.py
pyprt/pyprt/bin/libcom.esri.prt.core.so
pyprt/pyprt/bin/libglutess.so
pyprt/pyprt/bin/pyprt.cpython-310-x86_64-linux-gnu.so
pyprt/pyprt/lib/libcom.esri.prt.adaptors.so
pyprt/pyprt/lib/libcom.esri.prt.alembic.so
pyprt/pyprt/lib/libcom.esri.prt.codecs.so
pyprt/pyprt/lib/libcom.esri.prt.fbx.so
pyprt/pyprt/lib/libcom.esri.prt.oda.so
pyprt/pyprt/lib/libcom.esri.prt.usd.so
pyprt/pyprt/lib/liblibcrypto.so
pyprt/pyprt/lib/libprt_tbb.so.2
pyprt/pyprt/lib/libprt_usd_ms.so
pyprt/pyprt/lib/libpyprt_codec.so
pyprt/pyprt/lib/usd/plugInfo.json
pyprt/pyprt/lib/usd/ar/resources/plugInfo.json
pyprt/pyprt/lib/usd/ndr/resources/plugInfo.json
pyprt/pyprt/lib/usd/prtxResolver/resources/plugInfo.json
pyprt/pyprt/lib/usd/sdf/resources/plugInfo.json
pyprt/pyprt/lib/usd/usd/resources/generatedSchema.usda
pyprt/pyprt/lib/usd/usd/resources/plugInfo.json
pyprt/pyprt/lib/usd/usd/resources/codegenTemplates/api.h
pyprt/pyprt/lib/usd/usd/resources/codegenTemplates/plugInfo.json
pyprt/pyprt/lib/usd/usd/resources/codegenTemplates/schemaClass.cpp
pyprt/pyprt/lib/usd/usd/resources/codegenTemplates/schemaClass.h
pyprt/pyprt/lib/usd/usd/resources/codegenTemplates/tokens.cpp
pyprt/pyprt/lib/usd/usd/resources/codegenTemplates/tokens.h
pyprt/pyprt/lib/usd/usd/resources/codegenTemplates/wrapSchemaClass.cpp
pyprt/pyprt/lib/usd/usd/resources/codegenTemplates/wrapTokens.cpp
pyprt/pyprt/lib/usd/usd/resources/usd/schema.usda
pyprt/pyprt/lib/usd/usdGeom/resources/generatedSchema.usda
pyprt/pyprt/lib/usd/usdGeom/resources/plugInfo.json
pyprt/pyprt/lib/usd/usdGeom/resources/usdGeom/schema.usda
pyprt/pyprt/lib/usd/usdHydra/resources/plugInfo.json
pyprt/pyprt/lib/usd/usdHydra/resources/shaders/empty.glslfx
pyprt/pyprt/lib/usd/usdHydra/resources/shaders/shaderDefs.usda
pyprt/pyprt/lib/usd/usdLux/resources/generatedSchema.usda
pyprt/pyprt/lib/usd/usdLux/resources/plugInfo.json
pyprt/pyprt/lib/usd/usdLux/resources/usdLux/schema.usda
pyprt-1.11.0.10.dist-info/LICENSE
pyprt-1.11.0.10.dist-info/METADATA
pyprt-1.11.0.10.dist-info/WHEEL
pyprt-1.11.0.10.dist-info/top_level.txt
pyprt-1.11.0.10.dist-info/RECORD
