Metadata-Version: 2.1
Name: pyprt
Version: 1.11.0.10
Summary: Python bindings for the 'Procedural Runtime' (PRT) of CityEngine by Esri.
Author: Esri R&D Center Zurich
License: PyPRT is free for personal, educational, and non-commercial use. Commercial use requires at least one commercial license of the latest CityEngine version installed in the organization. Redistribution or web service offerings are not allowed unless expressly permitted. PyPRT is under the same license as the included [CityEngine SDK](https://github.com/Esri/esri-cityengine-sdk#licensing). An exception is the PyPRT source code (without CityEngine SDK, binaries, or object code), which is li
Project-URL: Source-Code, https://github.com/Esri/pyprt
Project-URL: Download, https://github.com/Esri/pyprt/releases
Project-URL: Documentation, https://github.com/Esri/pyprt/blob/master/README.md#documentation
Project-URL: Examples, https://github.com/Esri/pyprt-examples
Platform: Windows
Platform: Linux
Classifier: Development Status :: 5 - Production/Stable
Classifier: License :: Free for non-commercial use
Classifier: License :: OSI Approved :: Apache Software License
Classifier: Operating System :: Microsoft :: Windows
Classifier: Operating System :: Unix
Classifier: Programming Language :: C++
Classifier: Programming Language :: Python
Classifier: Programming Language :: Python :: 3 :: Only
Classifier: Topic :: Multimedia :: Graphics :: 3D Modeling
Classifier: Topic :: Scientific/Engineering
Classifier: Topic :: Software Development :: Libraries :: Python Modules
Requires-Python: <3.13,>=3.9
License-File: LICENSE
